plaidcloud/rpc/__init__.py
plaidcloud/rpc/config.py
plaidcloud/rpc/create_oauth_token.py
plaidcloud/rpc/database.py
plaidcloud/rpc/file_helpers.py
plaidcloud/rpc/functions.py
plaidcloud/rpc/logger.py
plaidcloud/rpc/orjson.py
plaidcloud/rpc/pcm_connection.py
plaidcloud/rpc/ratelimiter.py
plaidcloud/rpc/rpc_connect.py
plaidcloud/rpc/type_conversion.py
plaidcloud/rpc/utc.py
plaidcloud/rpc/connection/__init__.py
plaidcloud/rpc/connection/jsonrpc.py
plaidcloud/rpc/messytables/__init__.py
plaidcloud/rpc/messytables/any.py
plaidcloud/rpc/messytables/commas.py
plaidcloud/rpc/messytables/core.py
plaidcloud/rpc/messytables/dateparser.py
plaidcloud/rpc/messytables/error.py
plaidcloud/rpc/messytables/headers.py
plaidcloud/rpc/messytables/types.py
plaidcloud/rpc/messytables/util.py
plaidcloud/rpc/messytables/zip.py
plaidcloud/rpc/remote/__init__.py
plaidcloud/rpc/remote/auth.py
plaidcloud/rpc/remote/json_rpc_server.py
plaidcloud/rpc/remote/listener.py
plaidcloud/rpc/remote/rpc_common.py
plaidcloud/rpc/remote/rpc_tools.py
plaidcloud/rpc/tests/__init__.py
plaidcloud/rpc/tests/test_config.py
plaidcloud/rpc/tests/test_logger.py
plaidcloud/rpc/tests/test_orjson.py
plaidcloud/rpc/tests/remote/__init__.py
plaidcloud/rpc/tests/remote/test_auth.py
plaidcloud_rpc-1.6.9.dist-info/licenses/LICENSE
plaidcloud_rpc-1.6.9.dist-info/METADATA
plaidcloud_rpc-1.6.9.dist-info/WHEEL
plaidcloud_rpc-1.6.9.dist-info/top_level.txt
plaidcloud_rpc-1.6.9.dist-info/RECORD
